LICENSE.txt
MANIFEST.in
README.rst
requirements.txt
setup.py
py_winusb.egg-info/PKG-INFO
py_winusb.egg-info/SOURCES.txt
py_winusb.egg-info/dependency_links.txt
py_winusb.egg-info/entry_points.txt
py_winusb.egg-info/not-zip-safe
py_winusb.egg-info/requires.txt
py_winusb.egg-info/top_level.txt
pywinusb/__init__.py
pywinusb/__main__.py
pywinusb/creator.py
pywinusb/decorators.py
pywinusb/events.py
pywinusb/progress.py
pywinusb/window.py