Metadata-Version: 1.1
Name: py-winusb
Version: 0.2.0.1
Summary: Tool that helps with creating bootable Windows USB drives
Home-page: https://github.com/Mati365/pyWinUSB
Author: Mateusz Bagiński
Author-email: cziken58@gmail.com
License: MIT
Keywords: windows,usb,installer
Platform: linux
Classifier: Development Status :: 2 - Pre-Alpha
Classifier: Intended Audience :: Developers
Classifier: Intended Audience :: Information Technology
Classifier: Programming Language :: Python
Classifier: Programming Language :: Python :: 3
Classifier: Programming Language :: Python :: 3.3
Classifier: Programming Language :: Python :: 3.4
